distroinfo/__init__.py
distroinfo/exception.py
distroinfo/fetch.py
distroinfo/helpers.py
distroinfo/info.py
distroinfo/parse.py
distroinfo/query.py
distroinfo/repoman.py
distroinfo-0.6.3.dist-info/LICENSE
distroinfo-0.6.3.dist-info/METADATA
distroinfo-0.6.3.dist-info/WHEEL
distroinfo-0.6.3.dist-info/pbr.json
distroinfo-0.6.3.dist-info/top_level.txt
distroinfo-0.6.3.dist-info/RECORD
