Metadata-Version: 2.1
Name: distroinfo
Version: 0.6.3
Summary: python module for parsing, validating and querying distribution/packaging metadata stored in human readable and reviewable text/YAML files
Home-page: https://github.com/softwarefactory-project/distroinfo
Author: Jakub Ruzicka
Author-email: dev@lists.rdoproject.org
License: Apache Software License
Classifier: Programming Language :: Python
Classifier: Programming Language :: Python :: 3
Classifier: Programming Language :: Python :: 3.9
Classifier: Programming Language :: Python :: 3.10
Classifier: Programming Language :: Python :: 3.11
Classifier: Programming Language :: Python :: 3.12
Classifier: Programming Language :: Python :: 3.13
Classifier: Programming Language :: Python :: 3.14
Classifier: Environment :: OpenStack
Classifier: Intended Audience :: Information Technology
Classifier: Intended Audience :: System Administrators
Classifier: License :: OSI Approved :: Apache Software License
Classifier: Operating System :: POSIX :: Linux
Requires-Python: >=3.9
License-File: LICENSE
Requires-Dist: pbr >=6.0.0
Requires-Dist: PyYAML
Requires-Dist: requests
Requires-Dist: six
Provides-Extra: tests
Requires-Dist: pytest ; extra == 'tests'
Requires-Dist: pycodestyle ; extra == 'tests'
